{"version":1,"resource":"file:///home/saczky/CrisisPreventionProject/frontend/src/components/BaseFormCard/BaseFormCard.styles.ts","entries":[{"id":"nOAa.ts","timestamp":1716544016194},{"id":"Olfm.ts","timestamp":1716544139552},{"id":"XWGq.ts","timestamp":1716544284956},{"id":"5IYr.ts","timestamp":1716544308106},{"id":"zvLm.ts","timestamp":1716544327389},{"id":"gwJf.ts","source":"undoRedo.source","timestamp":1716544329709},{"id":"o0IO.ts","timestamp":1716544430271},{"id":"Fp7U.ts","timestamp":1716544442928},{"id":"c8gM.ts","timestamp":1716544494094},{"id":"y5wy.ts","timestamp":1716544514538},{"id":"VKcE.ts","timestamp":1716544546444},{"id":"7e0e.ts","timestamp":1716544634201},{"id":"l9PA.ts","timestamp":1716544734307},{"id":"e2u3.ts","timestamp":1716544756797},{"id":"JHqr.ts","timestamp":1716544767227},{"id":"xAlf.ts","timestamp":1716544780691},{"id":"uIM7.ts","timestamp":1716544850971},{"id":"r0Qi.ts","timestamp":1716544894281},{"id":"Tn2k.ts","source":"undoRedo.source","timestamp":1716544899241},{"id":"KQxp.ts","timestamp":1716544909221},{"id":"F5NX.ts","timestamp":1716544919941},{"id":"mjmK.ts","timestamp":1716544979134},{"id":"AN8l.ts","timestamp":1716545002711},{"id":"PNq7.ts","timestamp":1716545035944},{"id":"eMHU.ts","timestamp":1716545056388},{"id":"szpD.ts","timestamp":1716545079195},{"id":"SXKE.ts","timestamp":1716545263009},{"id":"SByo.ts","timestamp":1716545278652},{"id":"CbC5.ts","timestamp":1716545291116},{"id":"vMUv.ts","timestamp":1716545593891},{"id":"pi4p.ts","timestamp":1716545624024},{"id":"F3hP.ts","timestamp":1716545634094},{"id":"xXG5.ts","timestamp":1716545681531},{"id":"NTvg.ts","timestamp":1716545709932},{"id":"1WrS.ts","timestamp":1716545734628},{"id":"XCfC.ts","timestamp":1716545791075},{"id":"YjEE.ts","timestamp":1716545809922},{"id":"h6Br.ts","timestamp":1716547775756},{"id":"PsJy.ts","timestamp":1716547794019},{"id":"4tb0.ts","timestamp":1716547830846},{"id":"TyyS.ts","timestamp":1717506507225},{"id":"T8B3.ts","timestamp":1717506559895}]}