{"version":1,"resource":"file:///home/saczky/CrisisPreventionProject/frontend/tsconfig.json","entries":[{"id":"5In9.json","timestamp":1710491971671},{"id":"tjus.json","timestamp":1710492596878},{"id":"GuT2.json","timestamp":1710924132870},{"id":"CgZJ.json","timestamp":1711013146601},{"id":"40VP.json","timestamp":1712077580515},{"id":"I7Ba.json","timestamp":1712144251223},{"id":"uLLH.json","timestamp":1712145254633},{"id":"ezXm.json","timestamp":1712220295567},{"id":"nhwi.json","timestamp":1712323035940},{"id":"rKZE.json","timestamp":1712323542060},{"id":"cHPm.json","timestamp":1712565628489},{"id":"tAeR.json","timestamp":1712851099884},{"id":"WwqV.json","timestamp":1712851112710},{"id":"QDce.json","timestamp":1714038701746},{"id":"9u5z.json","timestamp":1714555904098},{"id":"kgkZ.json","timestamp":1714556350650},{"id":"dzZi.json","timestamp":1714556392999},{"id":"iqu9.json","timestamp":1714556421729},{"id":"nvr3.json","timestamp":1714556447680},{"id":"YMjv.json","timestamp":1714556559045},{"id":"qygR.json","timestamp":1715767711519},{"id":"Z9OU.json","timestamp":1716544126062},{"id":"1bpR.json","timestamp":1717399528909},{"id":"4vJ7.json","timestamp":1717576258382},{"id":"1olZ.json","timestamp":1717588146495}]}